{
  "id": "dropbox-educational-fr",
  "softwareId": "dropbox",
  "scenario": "educational",
  "lang": "fr",
  "title": "Cas d'usage éducatif de Dropbox",
  "description": "Utilisez Dropbox dans un cadre éducatif pour travaux académiques et matériel éducatif.",
  "useCaseDetails": {
    "industry": "Business & Productivity",
    "users": "Students, teachers, academic staff",
    "workflow": "Assignments, lesson plans, academic papers",
    "benefits": "Standard tools for academic document creation"
  },
  "reviewStatus": "pending",
  "aiGenerated": true,
  "metadata": {
    "created": "2026-07-19",
    "sourceLang": "en"
  },
  "_meta": {
    "source": "ai-generated-mock",
    "schema_version": "1.0.0",
    "unverified_fields": [
      "description",
      "useCaseDetails"
    ],
    "confidence": "medium"
  }
}