{
  "id": "google-meet-personal-fr",
  "softwareId": "google-meet",
  "scenario": "personal",
  "lang": "fr",
  "title": "Cas d'usage personnel de Google Meet",
  "description": "Utilisez Google Meet dans la vie personnelle pour appels vidéo familiaux et retrouvailles entre amis.",
  "useCaseDetails": {
    "industry": "Communication & Collaboration",
    "users": "Families, friends, community groups",
    "workflow": "Family video calls, friend catch-ups, virtual events",
    "benefits": "Free video calls keep personal connections strong across distances"
  },
  "reviewStatus": "pending",
  "aiGenerated": true,
  "metadata": {
    "created": "2026-07-19",
    "sourceLang": "en"
  },
  "_meta": {
    "source": "ai-generated-mock",
    "schema_version": "1.0.0",
    "unverified_fields": [
      "description",
      "useCaseDetails"
    ],
    "confidence": "medium"
  }
}