{
  "id": "corel-aftershot-alternatives-uk",
  "softwareId": "corel-aftershot",
  "lang": "uk",
  "title": "Відкриті альтернативи для Corel AfterShot",
  "description": "Нижче наведено список відкритих альтернатив для Corel AfterShot, безкоштовних з активною спільнотою.",
  "alternatives": [
    {
      "opensourceId": "darktable-2",
      "opensourceName": "Darktable",
      "matchScore": 0.95,
      "reason": "Офіційно рекомендована відкрита альтернатива, високо сумісна з Corel AfterShot"
    },
    {
      "opensourceId": "armorpaint",
      "opensourceName": "ArmorPaint",
      "matchScore": 0.85,
      "reason": "Відкрите ПЗ тієї ж категорії, доступне як альтернатива"
    },
    {
      "opensourceId": "blender",
      "opensourceName": "Blender",
      "matchScore": 0.8,
      "reason": "Відкрите ПЗ тієї ж категорії, доступне як альтернатива"
    },
    {
      "opensourceId": "blender-10",
      "opensourceName": "Blender",
      "matchScore": 0.75,
      "reason": "Відкрите ПЗ тієї ж категорії, доступне як альтернатива"
    },
    {
      "opensourceId": "blender-11",
      "opensourceName": "Blender",
      "matchScore": 0.7,
      "reason": "Відкрите ПЗ тієї ж категорії, доступне як альтернатива"
    }
  ],
  "reviewStatus": "pending",
  "aiGenerated": true,
  "metadata": {
    "created": "2026-07-19",
    "sourceLang": "en"
  },
  "_meta": {
    "source": "ai-generated-mock",
    "schema_version": "1.0.0",
    "unverified_fields": [
      "description",
      "alternatives"
    ],
    "confidence": "medium"
  }
}