{
  "id": "easeus-data-recovery-alternatives-fr",
  "softwareId": "easeus-data-recovery",
  "lang": "fr",
  "title": "Alternatives open-source pour EaseUS Data Recovery Wizard",
  "description": "Voici une liste d'alternatives open-source pour EaseUS Data Recovery Wizard, gratuites avec une communauté active.",
  "alternatives": [
    {
      "opensourceId": "testdisk-2",
      "opensourceName": "TestDisk & PhotoRec",
      "matchScore": 0.95,
      "reason": "Alternative open-source officiellement recommandée, hautement compatible avec EaseUS Data Recovery Wizard"
    },
    {
      "opensourceId": "albert",
      "opensourceName": "Albert",
      "matchScore": 0.85,
      "reason": "Logiciel open-source de même catégorie, disponible comme alternative"
    },
    {
      "opensourceId": "albert-2",
      "opensourceName": "Albert",
      "matchScore": 0.8,
      "reason": "Logiciel open-source de même catégorie, disponible comme alternative"
    },
    {
      "opensourceId": "albert-3",
      "opensourceName": "Albert",
      "matchScore": 0.75,
      "reason": "Logiciel open-source de même catégorie, disponible comme alternative"
    },
    {
      "opensourceId": "baobab",
      "opensourceName": "Baobab (Disk Usage Analyzer)",
      "matchScore": 0.7,
      "reason": "Logiciel open-source de même catégorie, disponible comme alternative"
    }
  ],
  "reviewStatus": "pending",
  "aiGenerated": true,
  "metadata": {
    "created": "2026-07-19",
    "sourceLang": "en"
  },
  "_meta": {
    "source": "ai-generated-mock",
    "schema_version": "1.0.0",
    "unverified_fields": [
      "description",
      "alternatives"
    ],
    "confidence": "medium"
  }
}