{
  "id": "panda-dome-alternatives-ru",
  "softwareId": "panda-dome",
  "lang": "ru",
  "title": "Открытые альтернативы для Panda Dome Advanced",
  "description": "Ниже приведен список открытых альтернатив для Panda Dome Advanced, бесплатных и с активным сообществом.",
  "alternatives": [
    {
      "opensourceId": "clamav-11",
      "opensourceName": "ClamAV",
      "matchScore": 0.95,
      "reason": "Официально рекомендованная открытая альтернатива, высоко совместимая с Panda Dome Advanced"
    },
    {
      "opensourceId": "bitwarden",
      "opensourceName": "Bitwarden",
      "matchScore": 0.85,
      "reason": "Открытое ПО той же категории, доступное как альтернатива"
    },
    {
      "opensourceId": "bitwarden-2",
      "opensourceName": "Bitwarden",
      "matchScore": 0.8,
      "reason": "Открытое ПО той же категории, доступное как альтернатива"
    },
    {
      "opensourceId": "bitwarden-3",
      "opensourceName": "Bitwarden",
      "matchScore": 0.75,
      "reason": "Открытое ПО той же категории, доступное как альтернатива"
    },
    {
      "opensourceId": "bitwarden-4",
      "opensourceName": "Bitwarden",
      "matchScore": 0.7,
      "reason": "Открытое ПО той же категории, доступное как альтернатива"
    }
  ],
  "reviewStatus": "pending",
  "aiGenerated": true,
  "metadata": {
    "created": "2026-07-19",
    "sourceLang": "en"
  },
  "_meta": {
    "source": "ai-generated-mock",
    "schema_version": "1.0.0",
    "unverified_fields": [
      "description",
      "alternatives"
    ],
    "confidence": "medium"
  }
}