{
  "id": "teamcity-alternatives-it",
  "softwareId": "teamcity",
  "lang": "it",
  "title": "Alternative open source per TeamCity",
  "description": "Di seguito è riportato un elenco di alternative open source per TeamCity, gratuite e con community attiva.",
  "alternatives": [
    {
      "opensourceId": "jenkins-5",
      "opensourceName": "Jenkins",
      "matchScore": 0.95,
      "reason": "Alternativa open source ufficialmente consigliata, altamente compatibile con TeamCity"
    },
    {
      "opensourceId": "dbeaver",
      "opensourceName": "DBeaver",
      "matchScore": 0.85,
      "reason": "Software open source della stessa categoria, disponibile come alternativa"
    },
    {
      "opensourceId": "gitea",
      "opensourceName": "Gitea",
      "matchScore": 0.8,
      "reason": "Software open source della stessa categoria, disponibile come alternativa"
    },
    {
      "opensourceId": "gitea-2",
      "opensourceName": "Gitea",
      "matchScore": 0.75,
      "reason": "Software open source della stessa categoria, disponibile come alternativa"
    },
    {
      "opensourceId": "gitea-3",
      "opensourceName": "Gitea",
      "matchScore": 0.7,
      "reason": "Software open source della stessa categoria, disponibile come alternativa"
    }
  ],
  "reviewStatus": "pending",
  "aiGenerated": true,
  "metadata": {
    "created": "2026-07-19",
    "sourceLang": "en"
  },
  "_meta": {
    "source": "ai-generated-mock",
    "schema_version": "1.0.0",
    "unverified_fields": [
      "description",
      "alternatives"
    ],
    "confidence": "medium"
  }
}